hint_calls.py
hint_calls_ida_plugin-0.1.2.dist-info/METADATA
hint_calls_ida_plugin-0.1.2.dist-info/WHEEL
hint_calls_ida_plugin-0.1.2.dist-info/entry_points.txt
hint_calls_ida_plugin-0.1.2.dist-info/top_level.txt
hint_calls_ida_plugin-0.1.2.dist-info/RECORD
