Metadata-Version: 2.4
Name: hint-calls-ida-plugin
Version: 0.1.2
Summary: IDA Pro plugin to display popup function hints for the referenced calls and strings
Author-email: Willi Ballenthin <willi.ballenthin@gmail.com>
License-Expression: Apache-2.0
Requires-Python: >=3.9
